garfield_get.py
setup.py
garfield_get.egg-info/PKG-INFO
garfield_get.egg-info/SOURCES.txt
garfield_get.egg-info/dependency_links.txt
garfield_get.egg-info/entry_points.txt
garfield_get.egg-info/not-zip-safe
garfield_get.egg-info/requires.txt
garfield_get.egg-info/top_level.txt